MANIFEST.in
README.md
setup.cfg
setup.py
.eggs/Cython-0.29.15-py3.7.egg/Cython/Compiler/Code.pxd
.eggs/Cython-0.29.15-py3.7.egg/Cython/Compiler/FlowControl.pxd
.eggs/Cython-0.29.15-py3.7.egg/Cython/Compiler/ParseTreeTransforms.pxd
.eggs/Cython-0.29.15-py3.7.egg/Cython/Compiler/Parsing.pxd
.eggs/Cython-0.29.15-py3.7.egg/Cython/Compiler/Scanning.pxd
.eggs/Cython-0.29.15-py3.7.egg/Cython/Compiler/Visitor.pxd
.eggs/Cython-0.29.15-py3.7.egg/Cython/Debugger/Tests/cfuncs.c
.eggs/Cython-0.29.15-py3.7.egg/Cython/Includes/openmp.pxd
.eggs/Cython-0.29.15-py3.7.egg/Cython/Includes/Deprecated/python.pxd
.eggs/Cython-0.29.15-py3.7.egg/Cython/Includes/Deprecated/python_bool.pxd
.eggs/Cython-0.29.15-py3.7.egg/Cython/Includes/Deprecated/python_buffer.pxd
.eggs/Cython-0.29.15-py3.7.egg/Cython/Includes/Deprecated/python_bytes.pxd
.eggs/Cython-0.29.15-py3.7.egg/Cython/Includes/Deprecated/python_cobject.pxd
.eggs/Cython-0.29.15-py3.7.egg/Cython/Includes/Deprecated/python_complex.pxd
.eggs/Cython-0.29.15-py3.7.egg/Cython/Includes/Deprecated/python_dict.pxd
.eggs/Cython-0.29.15-py3.7.egg/Cython/Includes/Deprecated/python_exc.pxd
.eggs/Cython-0.29.15-py3.7.egg/Cython/Includes/Deprecated/python_float.pxd
.eggs/Cython-0.29.15-py3.7.egg/Cython/Includes/Deprecated/python_function.pxd
.eggs/Cython-0.29.15-py3.7.egg/Cython/Includes/Deprecated/python_getargs.pxd
.eggs/Cython-0.29.15-py3.7.egg/Cython/Includes/Deprecated/python_instance.pxd
.eggs/Cython-0.29.15-py3.7.egg/Cython/Includes/Deprecated/python_int.pxd
.eggs/Cython-0.29.15-py3.7.egg/Cython/Includes/Deprecated/python_iterator.pxd
.eggs/Cython-0.29.15-py3.7.egg/Cython/Includes/Deprecated/python_list.pxd
.eggs/Cython-0.29.15-py3.7.egg/Cython/Includes/Deprecated/python_long.pxd
.eggs/Cython-0.29.15-py3.7.egg/Cython/Includes/Deprecated/python_mapping.pxd
.eggs/Cython-0.29.15-py3.7.egg/Cython/Includes/Deprecated/python_mem.pxd
.eggs/Cython-0.29.15-py3.7.egg/Cython/Includes/Deprecated/python_method.pxd
learn2learn_dev.egg-info/PKG-INFO
learn2learn_dev.egg-info/SOURCES.txt
learn2learn_dev.egg-info/dependency_links.txt
learn2learn_dev.egg-info/not-zip-safe
learn2learn_dev.egg-info/requires.txt
learn2learn_dev.egg-info/top_level.txt
