Metadata-Version: 2.1
Name: learn2learn-dev
Version: 0.1.0
Summary: PyTorch Meta-Learning Framework for Researchers
Home-page: https://github.com/learnables/learn2learn
Author: Debajyoti Datta, Ian bunner, Seb Arnold, Praateek Mahajan
Author-email: smr.arnold@gmail.com, praateekm@gmail.com
License: MIT
Download-URL: https://github.com/learnables/learn2learn/archive/0.1.0.zip
Platform: UNKNOWN
